odoo/addons/l10n_th_expense_withholding_tax/README.rst
odoo/addons/l10n_th_expense_withholding_tax/__init__.py
odoo/addons/l10n_th_expense_withholding_tax/__manifest__.py
odoo/addons/l10n_th_expense_withholding_tax/i18n/l10n_th_expense_withholding_tax.pot
odoo/addons/l10n_th_expense_withholding_tax/models/__init__.py
odoo/addons/l10n_th_expense_withholding_tax/models/hr_expense.py
odoo/addons/l10n_th_expense_withholding_tax/readme/CONTRIBUTORS.rst
odoo/addons/l10n_th_expense_withholding_tax/readme/DESCRIPTION.rst
odoo/addons/l10n_th_expense_withholding_tax/static/description/icon.png
odoo/addons/l10n_th_expense_withholding_tax/static/description/index.html
odoo/addons/l10n_th_expense_withholding_tax/tests/__init__.py
odoo/addons/l10n_th_expense_withholding_tax/tests/test_expense_withholding_tax.py
odoo/addons/l10n_th_expense_withholding_tax/views/hr_expense_view.xml
odoo14_addon_l10n_th_expense_withholding_tax-14.0.1.0.1.dev4.dist-info/METADATA
odoo14_addon_l10n_th_expense_withholding_tax-14.0.1.0.1.dev4.dist-info/WHEEL
odoo14_addon_l10n_th_expense_withholding_tax-14.0.1.0.1.dev4.dist-info/top_level.txt
odoo14_addon_l10n_th_expense_withholding_tax-14.0.1.0.1.dev4.dist-info/RECORD
